quranpy
