Metadata-Version: 2.1
Name: quranpy
Version: 1.1
Summary: Python Package to interact with the glorious Qu'ran
Home-page: https://github.com/niztg/quranpy
Author: nizcomix
License: MIT
Platform: UNKNOWN
Requires-Python: >=2.7, !=3.0.*, !=3.1.*, !=3.2.*, !=3.3.*, !=3.4.*
